<annotation>
        <folder>FOLDER</folder>
        <filename>289351545.jpg</filename>
        <path>data/scenes/val\289351545.jpg</path>
        <source>
                <database>Unknown</database>
        </source>
        <size>
                <width>720</width>
                <height>720</height>
                <depth>3</depth>
        </size>
 <object>
                <name>2s</name>
                <pose>Unspecified</pose>
                <truncated>0</truncated>
                <difficult>0</difficult>
                <bndbox>
                        <xmin>485</xmin>
                        <ymin>171</ymin>
                        <xmax>555</xmax>
                        <ymax>229</ymax>
                </bndbox>
        </object>
 <object>
                <name>2s</name>
                <pose>Unspecified</pose>
                <truncated>0</truncated>
                <difficult>0</difficult>
                <bndbox>
                        <xmin>164</xmin>
                        <ymin>186</ymin>
                        <xmax>233</xmax>
                        <ymax>245</ymax>
                </bndbox>
        </object>
 <object>
                <name>7s</name>
                <pose>Unspecified</pose>
                <truncated>0</truncated>
                <difficult>0</difficult>
                <bndbox>
                        <xmin>360</xmin>
                        <ymin>522</ymin>
                        <xmax>414</xmax>
                        <ymax>557</ymax>
                </bndbox>
        </object>
 <object>
                <name>7s</name>
                <pose>Unspecified</pose>
                <truncated>0</truncated>
                <difficult>0</difficult>
                <bndbox>
                        <xmin>562</xmin>
                        <ymin>463</ymin>
                        <xmax>614</xmax>
                        <ymax>498</ymax>
                </bndbox>
        </object>
</annotation>        
