<annotation>
        <folder>FOLDER</folder>
        <filename>322149738.jpg</filename>
        <path>data/scenes/val\322149738.jpg</path>
        <source>
                <database>Unknown</database>
        </source>
        <size>
                <width>720</width>
                <height>720</height>
                <depth>3</depth>
        </size>
 <object>
                <name>3s</name>
                <pose>Unspecified</pose>
                <truncated>0</truncated>
                <difficult>0</difficult>
                <bndbox>
                        <xmin>390</xmin>
                        <ymin>75</ymin>
                        <xmax>464</xmax>
                        <ymax>131</ymax>
                </bndbox>
        </object>
 <object>
                <name>3d</name>
                <pose>Unspecified</pose>
                <truncated>0</truncated>
                <difficult>0</difficult>
                <bndbox>
                        <xmin>413</xmin>
                        <ymin>156</ymin>
                        <xmax>489</xmax>
                        <ymax>197</ymax>
                </bndbox>
        </object>
 <object>
                <name>Ks</name>
                <pose>Unspecified</pose>
                <truncated>0</truncated>
                <difficult>0</difficult>
                <bndbox>
                        <xmin>414</xmin>
                        <ymin>234</ymin>
                        <xmax>494</xmax>
                        <ymax>269</ymax>
                </bndbox>
        </object>
 <object>
                <name>Ks</name>
                <pose>Unspecified</pose>
                <truncated>0</truncated>
                <difficult>0</difficult>
                <bndbox>
                        <xmin>184</xmin>
                        <ymin>461</ymin>
                        <xmax>263</xmax>
                        <ymax>495</ymax>
                </bndbox>
        </object>
</annotation>        
