<annotation>
        <folder>FOLDER</folder>
        <filename>690304946.jpg</filename>
        <path>data/scenes/val\690304946.jpg</path>
        <source>
                <database>Unknown</database>
        </source>
        <size>
                <width>720</width>
                <height>720</height>
                <depth>3</depth>
        </size>
 <object>
                <name>7c</name>
                <pose>Unspecified</pose>
                <truncated>0</truncated>
                <difficult>0</difficult>
                <bndbox>
                        <xmin>365</xmin>
                        <ymin>153</ymin>
                        <xmax>411</xmax>
                        <ymax>197</ymax>
                </bndbox>
        </object>
 <object>
                <name>2s</name>
                <pose>Unspecified</pose>
                <truncated>0</truncated>
                <difficult>0</difficult>
                <bndbox>
                        <xmin>352</xmin>
                        <ymin>327</ymin>
                        <xmax>395</xmax>
                        <ymax>371</ymax>
                </bndbox>
        </object>
 <object>
                <name>2s</name>
                <pose>Unspecified</pose>
                <truncated>0</truncated>
                <difficult>0</difficult>
                <bndbox>
                        <xmin>332</xmin>
                        <ymin>536</ymin>
                        <xmax>376</xmax>
                        <ymax>580</ymax>
                </bndbox>
        </object>
</annotation>        
